azure/mgmt/cosmosdb/__init__.py
azure/mgmt/cosmosdb/_configuration.py
azure/mgmt/cosmosdb/_cosmos_db_management_client.py
azure/mgmt/cosmosdb/_patch.py
azure/mgmt/cosmosdb/_serialization.py
azure/mgmt/cosmosdb/_version.py
azure/mgmt/cosmosdb/py.typed
azure/mgmt/cosmosdb/aio/__init__.py
azure/mgmt/cosmosdb/aio/_configuration.py
azure/mgmt/cosmosdb/aio/_cosmos_db_management_client.py
azure/mgmt/cosmosdb/aio/_patch.py
azure/mgmt/cosmosdb/aio/operations/__init__.py
azure/mgmt/cosmosdb/aio/operations/_cassandra_clusters_operations.py
azure/mgmt/cosmosdb/aio/operations/_cassandra_data_centers_operations.py
azure/mgmt/cosmosdb/aio/operations/_cassandra_resources_operations.py
azure/mgmt/cosmosdb/aio/operations/_collection_operations.py
azure/mgmt/cosmosdb/aio/operations/_collection_partition_operations.py
azure/mgmt/cosmosdb/aio/operations/_collection_partition_region_operations.py
azure/mgmt/cosmosdb/aio/operations/_collection_region_operations.py
azure/mgmt/cosmosdb/aio/operations/_database_account_region_operations.py
azure/mgmt/cosmosdb/aio/operations/_database_accounts_operations.py
azure/mgmt/cosmosdb/aio/operations/_database_operations.py
azure/mgmt/cosmosdb/aio/operations/_gremlin_resources_operations.py
azure/mgmt/cosmosdb/aio/operations/_locations_operations.py
azure/mgmt/cosmosdb/aio/operations/_mongo_db_resources_operations.py
azure/mgmt/cosmosdb/aio/operations/_notebook_workspaces_operations.py
azure/mgmt/cosmosdb/aio/operations/_operations.py
azure/mgmt/cosmosdb/aio/operations/_partition_key_range_id_operations.py
azure/mgmt/cosmosdb/aio/operations/_partition_key_range_id_region_operations.py
azure/mgmt/cosmosdb/aio/operations/_patch.py
azure/mgmt/cosmosdb/aio/operations/_percentile_operations.py
azure/mgmt/cosmosdb/aio/operations/_percentile_source_target_operations.py
azure/mgmt/cosmosdb/aio/operations/_percentile_target_operations.py
azure/mgmt/cosmosdb/aio/operations/_private_endpoint_connections_operations.py
azure_mgmt_cosmosdb-9.7.0.dist-info/LICENSE
azure_mgmt_cosmosdb-9.7.0.dist-info/METADATA
azure_mgmt_cosmosdb-9.7.0.dist-info/WHEEL
azure_mgmt_cosmosdb-9.7.0.dist-info/top_level.txt
azure_mgmt_cosmosdb-9.7.0.dist-info/RECORD
